{"2_k_clique_communities": [[["LG2", "LG3", "LG4", "LG5", "LG6", "LG7", "LH3", "LH4", "RG1", "RG2", "RG3", "RG4", "RH4", "RH5", "RH6", "RH7", "RH8"], 0.21411764705882352], [["LA4", "LA5", "LA6", "LA7", "LA8", "LB5", "LB6", "LB7", "LB8"], 0.20444444444444446], [["RF4", "RF5", "RF6", "RF7", "RF8"], 0.29999999999999993], [["LG3", "LG4", "LG5", "LG6", "LG7", "LH3", "LH4", "RG1", "RG2", "RG3", "RG4", "RH5", "RH6", "RH7", "RH8"], 0.2571428571428571], [["LA4", "LA5", "LA6", "LA7", "LA8", "LB5", "LB6", "LB7", "LB8"], 0.26], [["RF4", "RF5", "RF6", "RF7", "RF8", "RG1", "RG2", "RG3", "RG4", "RH5", "RH6", "RH7", "RH8"], 0.3174358974358974], [["RG1", "RG2", "RG3", "RG4", "RH5", "RH6", "RH7", "RH8"], 0.47], [["RG1", "RG2", "RG3", "RG4", "RH5", "RH6", "RH7", "RH8"], 0.4342857142857143], [["RG1", "RG2", "RG3", "RG4", "RH4", "RH5", "RH6", "RH7", "RH8"], 0.3433333333333334], [["RG1", "RG2", "RG3", "RG4", "RH4", "RH5", "RH6", "RH7", "RH8"], 0.37111111111111117], [["RA3", "RA4", "RA5", "RA6"], 0.22666666666666663], [["LA4", "LA5", "LA6", "LA7", "LA8", "LB5", "LB6"], 0.15619047619047616], [["RF4", "RF5", "RF6", "RF7", "RF8", "RG1", "RG2", "RG3", "RG4", "RH3", "RH4", "RH6", "RH7", "RH8"], 0.23472527472527474], [["RF4", "RF5", "RF6", "RF7", "RF8", "RG1", "RG2", "RG3", "RG4", "RH6", "RH7", "RH8"], 0.2284848484848485], [["RF4", "RF5", "RF6", "RF7", "RF8", "RG2", "RG3", "RG4", "RH6", "RH7", "RH8"], 0.22181818181818183], [["RG1", "RG2", "RG3", "RG4", "RH6", "RH7", "RH8"], 0.3466666666666666], [["RG2", "RG3", "RG4", "RH6", "RH7", "RH8"], 0.3733333333333333], [["LA5", "LA6", "LA7", "LA8", "LB6", "LB7", "LB8"], 0.3466666666666666], [["RF4", "RF5", "RF6", "RF7", "RF8", "RG1", "RG2", "RG3", "RG4", "RH2", "RH3", "RH4", "RH6", "RH7", "RH8"], 0.2857142857142857], [["LA6", "LA7", "LA8", "LB6", "LB7", "LB8"], 0.30666666666666664]], "3_k_clique_communities": [[["RF4", "RF5", "RF6", "RF7"], 0.39333333333333337], [["LA6", "LA7", "LA8", "LB7", "LB8"], 0.4], [["LA7", "LA8", "LB7", "LB8"], 0.56], [["RF4", "RF5", "RF6", "RF7", "RF8"], 0.4], [["LH4", "RG1", "RG2", "RG3", "RG4", "RH5", "RH6", "RH7", "RH8"], 0.42666666666666664], [["RF4", "RF5", "RF6", "RF7", "RG1", "RG2", "RG3", "RG4", "RH5", "RH6", "RH7", "RH8"], 0.33454545454545453], [["RG1", "RG2", "RG3", "RG4", "RH5", "RH6", "RH7", "RH8"], 0.47], [["RG1", "RG2", "RG3", "RG4", "RH5", "RH6", "RH7", "RH8"], 0.4342857142857143], [["RG1", "RG2", "RG3", "RG4", "RH5", "RH6", "RH7", "RH8"], 0.4342857142857143], [["LA1", "LA2", "LA3", "LB2"], 0.56], [["RG2", "RG3", "RG4", "RH6", "RH7"], 0.4], [["RG2", "RG3", "RG4", "RH6", "RH7", "RH8"], 0.44000000000000006], [["RG2", "RG3", "RG4", "RH6", "RH7", "RH8"], 0.5066666666666667], [["RG2", "RG3", "RG4", "RH6", "RH7", "RH8"], 0.5066666666666667], [["RG2", "RG3", "RG4", "RH6", "RH7", "RH8"], 0.5066666666666667], [["RG2", "RG3", "RG4", "RH6", "RH7", "RH8"], 0.5066666666666667], [["LA7", "LA8", "LB7", "LB8"], 0.39333333333333337], [["LA6", "LA7", "LA8", "LB6", "LB7", "LB8"], 0.5066666666666667], [["RF4", "RF5", "RF6", "RF7", "RF8", "RG2", "RG3", "RG4", "RH6", "RH7", "RH8"], 0.31272727272727274], [["LA6", "LA7", "LA8", "LB7", "LB8"], 0.4]], "4_k_clique_communities": [[["LA6", "LA7", "LA8", "LB6", "LB7", "LB8"], 0.44000000000000006], [["RG1", "RG2", "RG3", "RH5", "RH6", "RH7", "RH8"], 0.5371428571428571], [["LA7", "LA8", "LB7", "LB8"], 0.56], [["RF4", "RF5", "RF6", "RF7"], 0.56], [["RG1", "RG2", "RG3", "RG4", "RH5", "RH6", "RH7", "RH8"], 0.5057142857142857], [["LG3", "LG4", "LG5", "LH4"], 0.56], [["RG1", "RG2", "RG3", "RG4", "RH5", "RH6", "RH7", "RH8"], 0.47], [["RF4", "RF5", "RF6", "RF7"], 0.56], [["RF4", "RF5", "RF6", "RF7"], 0.56], [["RG1", "RG2", "RG3", "RG4", "RH5", "RH6", "RH7", "RH8"], 0.47], [["RE1", "RE2", "RE3", "RE4"], 0.56], [["RG2", "RG3", "RG4", "RH6", "RH7", "RH8"], 0.44000000000000006], [["RF4", "RF5", "RF6", "RF7"], 0.56], [["RG2", "RG3", "RG4", "RH6", "RH7", "RH8"], 0.5066666666666667], [["LA7", "LA8", "LB7", "LB8"], 0.56], [["RG2", "RG3", "RG4", "RH6", "RH7", "RH8"], 0.5066666666666667], [["RG3", "RG4", "RH6", "RH7", "RH8"], 0.5], [["LA6", "LA7", "LA8", "LB6", "LB7", "LB8"], 0.5066666666666667], [["RG2", "RG3", "RG4", "RH6", "RH7", "RH8"], 0.64], [["LA7", "LA8", "LB7", "LB8"], 0.56]], "girvan_newman": [[["LG2", "LG3", "LG4", "LG5", "LH3", "LH4", "RG1", "RG2", "RG3", "RG4", "RH4", "RH5", "RH6", "RH7", "RH8"], 0.3619047619047619], [["LG2", "LG3", "LG4", "LG5", "LH3", "LH4", "RG1", "RG2", "RG3", "RG4", "RH4", "RH5", "RH6", "RH7", "RH8"], 0.2857142857142857], [["RF4", "RF5", "RF6", "RF7", "RF8"], 0.29999999999999993], [["RE1", "RE2", "RE3", "RE4"], 0.39333333333333337], [["LA4", "LA5", "LA6", "LA7", "LA8", "LB5", "LB6", "LB7", "LB8"], 0.26], [["LG2", "LG3", "LG4", "LG5", "LG6", "LG7", "LG8", "LH4"], 0.14857142857142852], [["RF4", "RF5", "RF6", "RF7", "RF8"], 0.19999999999999996], [["RF4", "RF5", "RF6", "RF7", "RF8"], 0.4], [["RF4", "RF5", "RF6", "RF7", "RF8"], 0.4], [["LA1", "LA2", "LA3", "LB2"], 0.56], [["RE1", "RE2", "RE3", "RE4"], 0.56], [["LB1", "LB2", "LB3", "LB4"], 0.39333333333333337], [["RE1", "RE2", "RE3", "RE4"], 0.22666666666666663], [["RG1", "RG2", "RG3", "RG4", "RH6", "RH7", "RH8"], 0.3466666666666666], [["RG2", "RG3", "RG4", "RH6", "RH7", "RH8"], 0.5066666666666667], [["RG1", "RG2", "RG3", "RG4", "RH6", "RH7", "RH8"], 0.3466666666666666], [["RG2", "RG3", "RG4", "RH6", "RH7", "RH8"], 0.3733333333333333], [["LA5", "LA6", "LA7", "LA8", "LB6", "LB7", "LB8"], 0.3466666666666666], [["RF4", "RF5", "RF6", "RF7", "RF8", "RG1", "RG2", "RG3", "RG4", "RH6", "RH7", "RH8"], 0.2890909090909091], [["LA6", "LA7", "LA8", "LB6", "LB7", "LB8"], 0.30666666666666664]], "2_edge_current_flow_betweenness_partition": [[["LG2", "LG3", "LG4", "LG5", "LG6", "LG7", "LH3", "LH4", "RG1", "RG2", "RG3", "RG4", "RH4", "RH5", "RH6", "RH7", "RH8"], 0.21411764705882352], [["LA4", "LA5", "LA6", "LA7", "LA8", "LB5", "LB6", "LB7", "LB8"], 0.20444444444444446], [["RF4", "RF5", "RF6", "RF7", "RF8"], 0.29999999999999993], [["RE1", "RE2", "RE3", "RE4"], 0.39333333333333337], [["LA4", "LA5", "LA6", "LA7", "LA8", "LB5", "LB6", "LB7", "LB8"], 0.26], [["RF4", "RF5", "RF6", "RF7", "RF8", "RG1", "RG2", "RG3", "RG4", "RH5", "RH6", "RH7", "RH8"], 0.3174358974358974], [["RG1", "RG2", "RG3", "RG4", "RH5", "RH6", "RH7", "RH8"], 0.47], [["RG1", "RG2", "RG3", "RG4", "RH5", "RH6", "RH7", "RH8"], 0.4342857142857143], [["RG1", "RG2", "RG3", "RG4", "RH4", "RH5", "RH6", "RH7", "RH8"], 0.3433333333333334], [["LA1", "LA2", "LA3", "LB2"], 0.56], [["RE1", "RE2", "RE3", "RE4"], 0.56], [["LB1", "LB2", "LB3", "LB4"], 0.39333333333333337], [["RF4", "RF5", "RF6", "RF7", "RF8", "RG1", "RG2", "RG3", "RG4", "RH3", "RH4", "RH6", "RH7", "RH8"], 0.23472527472527474], [["RF4", "RF5", "RF6", "RF7", "RF8", "RG1", "RG2", "RG3", "RG4", "RH6", "RH7", "RH8"], 0.2284848484848485], [["RE1", "RE2", "RE3", "RE4"], 0.22666666666666663], [["RG1", "RG2", "RG3", "RG4", "RH6", "RH7", "RH8"], 0.3466666666666666], [["RG2", "RG3", "RG4", "RH6", "RH7", "RH8"], 0.3733333333333333], [["LA5", "LA6", "LA7", "LA8", "LB6", "LB7", "LB8"], 0.3466666666666666], [["RF4", "RF5", "RF6", "RF7", "RF8", "RG1", "RG2", "RG3", "RG4", "RH2", "RH3", "RH4", "RH6", "RH7", "RH8"], 0.2857142857142857], [["LA6", "LA7", "LA8", "LB6", "LB7", "LB8"], 0.30666666666666664]], "3_edge_current_flow_betweenness_partition": [[["LG2", "LG3", "LG4", "LG5", "LG6", "LG7", "LH3", "LH4", "RG1", "RG2", "RG3", "RG4", "RH4", "RH5", "RH6", "RH7", "RH8"], 0.21411764705882352], [["LA4", "LA5", "LA6", "LA7", "LA8", "LB5", "LB6", "LB7", "LB8"], 0.20444444444444446], [["RF4", "RF5", "RF6", "RF7", "RF8"], 0.29999999999999993], [["RE1", "RE2", "RE3", "RE4"], 0.39333333333333337], [["LA4", "LA5", "LA6", "LA7", "LA8", "LB5", "LB6", "LB7", "LB8"], 0.26], [["RF4", "RF5", "RF6", "RF7", "RF8", "RG1", "RG2", "RG3", "RG4", "RH5", "RH6", "RH7", "RH8"], 0.3174358974358974], [["RG1", "RG2", "RG3", "RG4", "RH5", "RH6", "RH7", "RH8"], 0.47], [["RG1", "RG2", "RG3", "RG4", "RH5", "RH6", "RH7", "RH8"], 0.4342857142857143], [["RG1", "RG2", "RG3", "RG4", "RH4", "RH5", "RH6", "RH7", "RH8"], 0.3433333333333334], [["LA1", "LA2", "LA3", "LB2"], 0.56], [["RE1", "RE2", "RE3", "RE4"], 0.56], [["LB1", "LB2", "LB3", "LB4"], 0.39333333333333337], [["RF4", "RF5", "RF6", "RF7", "RF8", "RG1", "RG2", "RG3", "RG4", "RH3", "RH4", "RH6", "RH7", "RH8"], 0.23472527472527474], [["RF4", "RF5", "RF6", "RF7", "RF8", "RG1", "RG2", "RG3", "RG4", "RH6", "RH7", "RH8"], 0.2284848484848485], [["RE1", "RE2", "RE3", "RE4"], 0.22666666666666663], [["RG1", "RG2", "RG3", "RG4", "RH6", "RH7", "RH8"], 0.3466666666666666], [["RG2", "RG3", "RG4", "RH6", "RH7", "RH8"], 0.3733333333333333], [["LA5", "LA6", "LA7", "LA8", "LB6", "LB7", "LB8"], 0.3466666666666666], [["RF4", "RF5", "RF6", "RF7", "RF8", "RG1", "RG2", "RG3", "RG4", "RH2", "RH3", "RH4", "RH6", "RH7", "RH8"], 0.2857142857142857], [["LA6", "LA7", "LA8", "LB6", "LB7", "LB8"], 0.30666666666666664]], "4_edge_current_flow_betweenness_partition": [[["LG2", "LG3", "LG4", "LG5", "LG6", "LG7", "LH3", "LH4", "RG1", "RG2", "RG3", "RG4", "RH4", "RH5", "RH6", "RH7", "RH8"], 0.21411764705882352], [["LA4", "LA5", "LA6", "LA7", "LA8", "LB5", "LB6", "LB7", "LB8"], 0.20444444444444446], [["RF4", "RF5", "RF6", "RF7", "RF8"], 0.29999999999999993], [["RE1", "RE2", "RE3", "RE4"], 0.39333333333333337], [["LA4", "LA5", "LA6", "LA7", "LA8", "LB5", "LB6", "LB7", "LB8"], 0.26], [["RF4", "RF5", "RF6", "RF7", "RF8", "RG1", "RG2", "RG3", "RG4", "RH5", "RH6", "RH7", "RH8"], 0.3174358974358974], [["RG1", "RG2", "RG3", "RG4", "RH5", "RH6", "RH7", "RH8"], 0.47], [["RG1", "RG2", "RG3", "RG4", "RH5", "RH6", "RH7", "RH8"], 0.4342857142857143], [["RG1", "RG2", "RG3", "RG4", "RH4", "RH5", "RH6", "RH7", "RH8"], 0.3433333333333334], [["LA1", "LA2", "LA3", "LB2"], 0.56], [["RE1", "RE2", "RE3", "RE4"], 0.56], [["LB1", "LB2", "LB3", "LB4"], 0.39333333333333337], [["RF4", "RF5", "RF6", "RF7", "RF8", "RG1", "RG2", "RG3", "RG4", "RH3", "RH4", "RH6", "RH7", "RH8"], 0.23472527472527474], [["RF4", "RF5", "RF6", "RF7", "RF8", "RG1", "RG2", "RG3", "RG4", "RH6", "RH7", "RH8"], 0.2284848484848485], [["RE1", "RE2", "RE3", "RE4"], 0.22666666666666663], [["RG1", "RG2", "RG3", "RG4", "RH6", "RH7", "RH8"], 0.3466666666666666], [["RG2", "RG3", "RG4", "RH6", "RH7", "RH8"], 0.3733333333333333], [["LA5", "LA6", "LA7", "LA8", "LB6", "LB7", "LB8"], 0.3466666666666666], [["RF4", "RF5", "RF6", "RF7", "RF8", "RG1", "RG2", "RG3", "RG4", "RH2", "RH3", "RH4", "RH6", "RH7", "RH8"], 0.2857142857142857], [["LA6", "LA7", "LA8", "LB6", "LB7", "LB8"], 0.30666666666666664]], "greedy_modularity_communities": [[["LG2", "LG3", "LG4", "LG5", "LG6", "LG7", "LH3", "LH4", "RG1", "RG2", "RG3", "RG4", "RH4", "RH5", "RH6", "RH7", "RH8"], 0.21411764705882352], [["LA4", "LA5", "LA6", "LA7", "LA8", "LB5", "LB6", "LB7", "LB8"], 0.20444444444444446], [["RF4", "RF5", "RF6", "RF7", "RF8"], 0.29999999999999993], [["RE1", "RE2", "RE3", "RE4"], 0.39333333333333337], [["LA4", "LA5", "LA6", "LA7", "LA8", "LB5", "LB6", "LB7", "LB8"], 0.26], [["RF4", "RF5", "RF6", "RF7", "RF8", "RG1", "RG2", "RG3", "RG4", "RH5", "RH6", "RH7", "RH8"], 0.3174358974358974], [["RG1", "RG2", "RG3", "RG4", "RH5", "RH6", "RH7", "RH8"], 0.47], [["RG1", "RG2", "RG3", "RG4", "RH5", "RH6", "RH7", "RH8"], 0.4342857142857143], [["RG1", "RG2", "RG3", "RG4", "RH4", "RH5", "RH6", "RH7", "RH8"], 0.3433333333333334], [["LA1", "LA2", "LA3", "LB2"], 0.56], [["RE1", "RE2", "RE3", "RE4"], 0.56], [["LB1", "LB2", "LB3", "LB4"], 0.39333333333333337], [["RE1", "RE2", "RE3", "RE4"], 0.22666666666666663], [["RF4", "RF5", "RF6", "RF7", "RF8", "RG1", "RG2", "RG3", "RG4", "RH6", "RH7", "RH8"], 0.2284848484848485], [["RG2", "RG3", "RG4", "RH6", "RH7", "RH8"], 0.5066666666666667], [["RG1", "RG2", "RG3", "RG4", "RH6", "RH7", "RH8"], 0.3466666666666666], [["RG2", "RG3", "RG4", "RH6", "RH7", "RH8"], 0.3733333333333333], [["LA5", "LA6", "LA7", "LA8", "LB6", "LB7", "LB8"], 0.3466666666666666], [["RF4", "RF5", "RF6", "RF7", "RF8", "RG1", "RG2", "RG3", "RG4", "RH6", "RH7", "RH8"], 0.2890909090909091], [["LA6", "LA7", "LA8", "LB6", "LB7", "LB8"], 0.30666666666666664]], "louvain_communities": [[["LH3", "LH4", "RG1", "RG2", "RG3", "RG4", "RH4", "RH5", "RH6", "RH7", "RH8"], 0.349090909090909], [["RG1", "RG2", "RG3", "RG4", "RH4", "RH5", "RH6", "RH7", "RH8"], 0.3433333333333334], [["RG1", "RG2", "RG3", "RG4", "RH5", "RH6", "RH7", "RH8"], 0.47], [["RG1", "RG2", "RG3", "RG4", "RH5", "RH6", "RH7", "RH8"], 0.3985714285714286], [["RG1", "RG2", "RG3", "RG4", "RH5", "RH6", "RH7", "RH8"], 0.5057142857142857], [["RG1", "RG2", "RG3", "RG4", "RH5", "RH6", "RH7", "RH8"], 0.4342857142857143], [["RG1", "RG2", "RG3", "RG4", "RH5", "RH6", "RH7", "RH8"], 0.47], [["RG1", "RG2", "RG3", "RG4", "RH5", "RH6", "RH7", "RH8"], 0.4342857142857143], [["RF4", "RF5", "RF6", "RF7", "RF8"], 0.4], [["LA1", "LA2", "LA3", "LB2"], 0.56], [["RE1", "RE2", "RE3", "RE4"], 0.56], [["LB1", "LB2", "LB3", "LB4"], 0.39333333333333337], [["RF4", "RF5", "RF6", "RF7", "RF8"], 0.4], [["RG1", "RG2", "RG3", "RG4", "RH6", "RH7", "RH8"], 0.3466666666666666], [["RG2", "RG3", "RG4", "RH6", "RH7", "RH8"], 0.5066666666666667], [["RG1", "RG2", "RG3", "RG4", "RH6", "RH7", "RH8"], 0.3466666666666666], [["RG2", "RG3", "RG4", "RH6", "RH7", "RH8"], 0.3733333333333333], [["LA5", "LA6", "LA7", "LA8", "LB6", "LB7", "LB8"], 0.3466666666666666], [["RG1", "RG2", "RG3", "RG4", "RH6", "RH7", "RH8"], 0.44190476190476186], [["LA6", "LA7", "LA8", "LB6", "LB7", "LB8"], 0.30666666666666664]], "kernighan_lin_bisection": [[["LA1", "LB1", "LB4", "LC4", "LE2", "LF2", "LF3", "LF4", "LF5", "LF6", "RA2", "RA3", "RA4", "RA5", "RA6", "RA8", "RB1", "RB7", "RC1", "RC5", "RE6", "RE8", "RF2"], 0], [["LA1", "LA2", "LA3", "LC3", "LC5", "LC6", "LC7", "LD4", "LD5", "LD7", "LE1", "LF1", "LF2", "LF3", "LF4", "LF6", "LF7", "LG1", "LG2", "LG3", "LG4", "LG5", "LG6", "LG7", "LG8", "LH1", "LH2", "LH3", "LH4", "RA2", "RA3", "RA4", "RA5", "RA6", "RA8", "RB5", "RB7", "RB8", "RC1", "RC2", "RC7", "RC8", "RD1", "RD6", "RE3", "RE5", "RE8", "RF1", "RG1", "RG2", "RG3", "RG4", "RG5", "RG7", "RH2", "RH4", "RH5", "RH6", "RH7", "RH8"], 0], [["LA1", "LC2", "LC4", "LD1", "LD2", "LD7", "LE1", "LG2", "LG3", "LG4", "LG5", "LG6", "LG7", "LG8", "LH2", "LH3", "LH4", "RB3", "RB4", "RB6", "RD1", "RF3", "RF4", "RF5", "RF6", "RF7", "RF8", "RG1", "RG2", "RG3", "RG4", "RH5", "RH6", "RH7", "RH8"], 0], [["LA1", "LA3", "LA4", "LA5", "LA6", "LA7", "LA8", "LB2", "LB3", "LB5", "LB6", "LB7", "LB8", "LC1", "LC2", "LC3", "LC4", "LC8", "LD1", "LD5", "LD7", "LE1", "LE3", "LE4", "LF1", "LF3", "LF4", "LF5", "LG8", "LH1", "LH2", "RA7", "RB1", "RB4", "RB5", "RB6", "RB7", "RC2", "RC3", "RC4", "RC5", "RC6", "RC8", "RD1", "RD4", "RD5", "RD6", "RD7", "RD8", "RE1", "RE2", "RE3", "RE4", "RE5", "RE6", "RE7", "RE8", "RG7", "RG8", "RH2"], 0], [["LA1", "LD4", "LD6", "LD7", "LF5", "LG1", "LG2", "LG3", "LG4", "LG5", "LG6", "LG7", "LH3", "LH4", "RA8", "RD1", "RF3", "RG1", "RG2", "RG3", "RG4", "RG8", "RH3", "RH5", "RH6", "RH7", "RH8"], 0], [["LA1", "LA2", "LA3", "LA4", "LA5", "LA6", "LA7", "LA8", "LB5", "LB6", "LB7", "LB8", "LC4", "LC5", "LC6", "LC7", "LC8", "LD2", "LE1", "LF2", "LF3", "LF4", "LF6", "LF7", "LG1", "LG2", "LG3", "LG4", "LG5", "LG6", "LH2", "LH4", "RA2", "RA3", "RB7", "RB8", "RC4", "RC5", "RC6", "RD2", "RD4", "RD7", "RD8", "RE1", "RF1", "RF4", "RF5", "RF6", "RF7", "RF8", "RG1", "RG2", "RG3", "RG4", "RG6", "RH1", "RH5", "RH6", "RH7", "RH8"], 0], [["LA1", "LC2", "LD2", "LD3", "LD4", "LE1", "LE2", "LE3", "LE4", "LF5", "LH1", "RA4", "RA5", "RA6", "RA8", "RC1", "RC2", "RD1", "RE1", "RE2", "RE3", "RE4", "RE7", "RE8", "RH4"], 0], [["LA1", "LC1", "LC2", "LD7", "LE1", "LE3", "LF1", "LG5", "LG6", "LG7", "LG8", "RC1", "RE1", "RE5", "RE7", "RF4", "RF5", "RF6", "RF7", "RF8", "RG1", "RG2", "RG3", "RG4", "RH1", "RH5", "RH6", "RH7", "RH8"], 0], [["LA1", "LA4", "LA5", "LA6", "LA7", "LA8", "LB2", "LB4", "LB5", "LB6", "LB7", "LB8", "LC1", "LC2", "LC4", "LC5", "LC6", "LC7", "LC8", "LF3", "LF4", "LG1", "LH1", "LH2", "RA3", "RA4", "RA5", "RA6", "RA7", "RA8", "RB1", "RB2", "RB7", "RC1", "RD1", "RD3", "RD6", "RE8", "RF3", "RH2", "RH3"], 0], [["LA1", "LA2", "LA3", "LA7", "LA8", "LB2", "LB4", "LB7", "LB8", "LC1", "LC3", "LC4", "LD1", "LD2", "LD7", "LF1", "LF2", "LF3", "LF4", "LF5", "LG1", "LG2", "LG3", "LG4", "LG5", "LG6", "LG7", "LG8", "LH2", "LH3", "LH4", "RA2", "RA3", "RA4", "RA5", "RA6", "RA7", "RA8", "RB3", "RB4", "RB8", "RC2", "RC3", "RC4", "RC5", "RC7", "RC8", "RD2", "RD3", "RD5", "RD6", "RE1", "RE2", "RE3", "RE4", "RE5", "RE8", "RG5", "RG7", "RG8"], 0], [["LA1", "LA3", "LA4", "LA5", "LB2", "LB3", "LB4", "LB5", "LC4", "LC5", "LC6", "LC7", "LD4", "LD5", "LE1", "LE2", "LE3", "LE4", "LF1", "LF2", "LG1", "LH1", "RA2", "RA7", "RA8", "RB1", "RB4", "RB5", "RB6", "RB7", "RC3", "RC4", "RC5", "RC6", "RC8", "RD1", "RD2", "RD3", "RD5", "RD6", "RD7", "RD8", "RE1", "RE2", "RE3", "RE4", "RE5", "RE6", "RE8", "RF1", "RG1", "RG2", "RG3", "RG4", "RG7", "RH3", "RH4", "RH6", "RH7", "RH8"], 0], [["LA1", "LA2", "LA3", "LA4", "LA5", "LA6", "LA7", "LA8", "LB5", "LB6", "LB7", "LC3", "LC4", "LC5", "LC6", "LC7", "LF6", "RB5", "RB6", "RC2", "RD4", "RE6", "RG6", "RH1"], 0], [["LA1", "LC4", "LC5", "LC6", "LC7", "LC8", "LD7", "LE4", "LF3", "LF4", "LF5", "LF6", "LH3", "LH4", "RB3", "RB7", "RC1", "RC7", "RC8", "RD2", "RE1", "RE2", "RE3", "RE4", "RE7", "RE8", "RF1", "RF3", "RF4", "RF5", "RF6", "RF7", "RF8", "RH1", "RH2"], 0], [["LA1", "LA5", "LA6", "LA7", "LA8", "LB1", "LB5", "LB6", "LB7", "LB8", "LC2", "LD1", "LD4", "LD5", "LD6", "LD7", "LE1", "LE4", "LF1", "LF3", "LF4", "LF5", "LF8", "RA2", "RA3", "RA4", "RA5", "RA6", "RA7", "RB5", "RB6", "RB7", "RB8", "RC8", "RE1", "RE2", "RE3", "RE4", "RE5", "RE6", "RE7", "RF1", "RF2", "RF3", "RF4", "RF5", "RF6", "RF7", "RF8", "RG1", "RG2", "RG3", "RG4", "RG5", "RG6", "RG7", "RH1", "RH6", "RH7", "RH8"], 0], [["LA1", "LA4", "LB3", "LC2", "LD3", "LE4", "LF1", "LF3", "LF4", "LF5", "LF6", "LG1", "LG3", "LG4", "LG5", "LG6", "LG7", "LG8", "LH1", "LH2", "RA1", "RA2", "RA3", "RA4", "RA5", "RA6", "RA7", "RB4", "RB5", "RB6", "RB8", "RC1", "RC2", "RC3", "RC4", "RC5", "RD4", "RD5", "RD6", "RD7", "RD8", "RE1", "RE2", "RE3", "RE4", "RE6", "RE7", "RF3", "RG1", "RG2", "RG3", "RG4", "RG6", "RG7", "RH1", "RH2", "RH5", "RH6", "RH7", "RH8"], 0], [["LA1", "LA4", "LB3", "LB4", "LC1", "LC5", "LC6", "LC7", "LC8", "LD4", "LD5", "LD6", "LD7", "LF1", "LF8", "RA1", "RA3", "RA4", "RA5", "RA6", "RA7", "RB2", "RB3", "RB4", "RB5", "RB6", "RC4", "RD4", "RE5", "RE7", "RF2", "RF4", "RF5", "RF6", "RF7", "RF8", "RG6", "RG7"], 0], [["LA1", "LA5", "LA6", "LA7", "LA8", "LB1", "LB3", "LB6", "LB7", "LB8", "LC3", "LD5", "LE1", "LE2", "LE3", "LE4", "LF2", "LG1", "LG3", "LG4", "LG5", "LG6", "LG7", "LG8", "LH3", "LH4", "RB3", "RC5", "RD2", "RD4", "RD5", "RD6", "RE6", "RE8", "RF3", "RF4", "RF5", "RF6", "RF7", "RF8", "RG5", "RG7", "RG8"], 0], [["LA1", "LA2", "LA3", "LA4", "LB1", "LB2", "LB3", "LB4", "LC3", "LC4", "LC5", "LC6", "LC7", "LC8", "LD1", "LD3", "LD5", "LD6", "LD7", "LF2", "LF3", "LF4", "LF5", "LF6", "LF7", "LF8", "LG3", "LG4", "LG5", "LG6", "LH1", "LH2", "LH3", "LH4", "RB1", "RB2", "RB7", "RC3", "RC5", "RC6", "RC8", "RD4", "RD7", "RD8", "RE6", "RF4", "RF5", "RF6", "RF7", "RF8", "RG1", "RG2", "RG3", "RG4", "RG7", "RH1", "RH2", "RH6", "RH7", "RH8"], 0], [["LA1", "LB1", "LB2", "LB4", "LC2", "LC4", "LC5", "LC6", "LC7", "LC8", "LD5", "LD7", "LE1", "LE2", "LE3", "LE4", "LF2", "LF3", "LF4", "LF5", "LF6", "LF7", "LF8", "LG2", "LG3", "LG4", "LG5", "LG6", "LG7", "LG8", "LH1", "LH2", "RA2", "RB1", "RB3", "RB4", "RB7", "RB8", "RC2", "RC8", "RD2", "RD5", "RE1", "RE2", "RE3", "RE4", "RE5", "RE7", "RG1", "RG2", "RG3", "RG4", "RG5", "RG8", "RH2", "RH3", "RH4", "RH6", "RH7", "RH8"], 0], [["LA1", "LA2", "LA4", "LB1", "LB2", "LB3", "LB5", "LC1", "LD1", "LD2", "LD5", "LD6", "LD7", "LF3", "LF4", "LF5", "LF6", "LF7", "LF8", "LG1", "LG2", "LG3", "LG4", "LG5", "LG6", "LG7", "LG8", "LH1", "LH3", "LH4", "RA1", "RA2", "RA4", "RB2", "RB7", "RB8", "RC4", "RC5", "RC6", "RC8", "RD1", "RD2", "RD3", "RD4", "RD5", "RD6", "RE6", "RF1", "RF3", "RG1", "RG2", "RG3", "RG4", "RG6", "RH3", "RH4", "RH5", "RH6", "RH7", "RH8"], 0]]}