{"2_k_clique_communities": [[["PFG1", "PFG2", "PFG3", "PP2", "PP3", "PA1", "PA2", "PA3", "PA4"], 0.5377777777777778]], "3_k_clique_communities": [[["PFG1", "PFG2", "PFG3", "PP2", "PA1", "PA2", "PA3", "PA4"], 0.6842857142857143]], "4_k_clique_communities": [[["CR1", "OR4", "OR5", "OR6", "OR7", "OR8", "OR9", "OR10", "FT1", "FT2"], 0.7333333333333334]], "girvan_newman": [[["PFG1", "PFG2", "PFG3", "PP2", "PP3", "PA1", "PA2", "PA3", "PA4"], 0.5377777777777778]], "2_edge_current_flow_betweenness_partition": [[["PFG1", "PFG2", "PFG3", "PP2", "PP3", "PA1", "PA2", "PA3", "PA4"], 0.5377777777777778]], "3_edge_current_flow_betweenness_partition": [[["PFG1", "PFG2", "PFG3", "PP2", "PP3", "PA1", "PA2", "PA3", "PA4"], 0.5377777777777778]], "4_edge_current_flow_betweenness_partition": [[["PFG1", "PFG2", "PFG3", "PP2", "PP3", "PA1", "PA2", "PA3", "PA4"], 0.5377777777777778]], "greedy_modularity_communities": [[["PFG1", "PFG2", "PFG3", "PP2", "PP3", "PA1", "PA2", "PA3", "PA4"], 0.5377777777777778]], "louvain_communities": [[["PFG1", "PFG2", "PFG3", "PP2", "PP3", "PA1", "PA2", "PA3", "PA4"], 0.5377777777777778]], "kernighan_lin_bisection": [[["TP1", "TP2", "TP3", "TP4", "TP5", "TP6", "TP7", "TP8", "TB1", "TB2", "TB3", "TB4", "TB5", "TB6", "TB7", "A3", "A4", "A5", "A6", "A7", "A8", "A9", "B2", "B3", "B4", "B5", "B6", "B7", "B8", "B9", "C8", "C9", "GPH9", "OT6", "OT8", "FCA1", "FCA2", "FCA3", "FCA4", "FCA5", "FCA6", "FCA7", "FCA8", "GL1", "GL2", "GL3", "GL4", "GL5", "Cu5", "Cu6", "Cu8", "PFG9", "PA6", "GC1", "GC6", "GC7", "PI1", "PI4", "PI9", "LP3", "FD9", "FP9", "CR7", "CR9", "R1", "R3", "R4", "R5", "R6", "R8", "R9", "OR1", "OR12", "OR13", "OF1", "OF2", "OC3", "OP2"], 0]]}