{"2_k_clique_communities": [[["RA02", "RB01", "RB02", "RB03", "RC02", "RC03", "RC04", "RC05"], 0.11285714285714282], [["RB01", "RC01", "RC02", "RC03"], 0.22666666666666663], [["RB02", "RB03", "RC03", "RC04", "RC05"], 0.29999999999999993], [["LE01", "LG01", "LG03", "LG05"], 0.06]], "3_k_clique_communities": [[["LG03", "LG05", "RF04", "RF05", "RF06", "RG01", "RG02", "RG03", "RI03", "RI04", "RI05", "RJ05", "RJ06", "RJ07"], 0.32263736263736265], [["LG03", "LG05", "RF03", "RF04", "RF05", "RF06", "RF07", "RG01", "RG02", "RG03", "RI03", "RI04", "RJ05", "RJ06", "RJ07"], 0.34285714285714286], [["RF03", "RF04", "RF05", "RF06", "RG01", "RG02", "RG03", "RI03", "RI04", "RI05", "RJ03", "RJ04", "RJ05", "RJ06", "RJ07"], 0.34285714285714286], [["RF03", "RF04", "RF05", "RF06", "RG01", "RG02", "RG03", "RI03", "RI04", "RI05", "RI06", "RJ03", "RJ04", "RJ05", "RJ06", "RJ07"], 0.32666666666666666]], "4_k_clique_communities": [[["RF04", "RF05", "RI03", "RI04", "RJ05", "RJ06"], 0.64], [["RF04", "RF05", "RI03", "RI04", "RI05", "RJ05", "RJ06"], 0.5371428571428571], [["RF04", "RF05", "RI03", "RI04", "RJ05", "RJ06"], 0.64], [["RG01", "RG02", "RG03", "RJ07"], 0.56]], "girvan_newman": [[["RA02", "RB01", "RB02", "RB03", "RC02", "RC03", "RC04", "RC05"], 0.11285714285714282], [["RB01", "RC01", "RC02", "RC03"], 0.22666666666666663], [["RF03", "RF04", "RF05", "RF06", "RF07", "RF08", "RG01", "RG02", "RG03", "RI03", "RI04", "RI05", "RJ03", "RJ04", "RJ05", "RJ06", "RJ07"], 0.19941176470588234], [["RF03", "RF04", "RF05", "RF06", "RG01", "RG02", "RG03", "RI03", "RI04", "RI05", "RI06", "RI07", "RI08", "RJ03", "RJ04", "RJ05", "RJ06", "RJ07"], 0.18065359477124182]], "2_edge_current_flow_betweenness_partition": [[["RA02", "RB01", "RB02", "RB03", "RC02", "RC03", "RC04", "RC05"], 0.11285714285714282], [["RB01", "RC01", "RC02", "RC03"], 0.22666666666666663], [["LB05", "LB07", "LC03", "LC05"], 0.06], [["RE04", "RE05", "RE06", "RE07"], 0.06]], "3_edge_current_flow_betweenness_partition": [[["RA02", "RB01", "RB02", "RB03", "RC02", "RC03", "RC04", "RC05"], 0.11285714285714282], [["RB01", "RC01", "RC02", "RC03"], 0.22666666666666663], [["LB05", "LB07", "LC03", "LC05"], 0.06], [["RE04", "RE05", "RE06", "RE07"], 0.06]], "4_edge_current_flow_betweenness_partition": [[["RA02", "RB01", "RB02", "RB03", "RC02", "RC03", "RC04", "RC05"], 0.11285714285714282], [["RB01", "RC01", "RC02", "RC03"], 0.22666666666666663], [["LB05", "LB07", "LC03", "LC05"], 0.06], [["RE04", "RE05", "RE06", "RE07"], 0.06]], "greedy_modularity_communities": [[["RF03", "RF04", "RF05", "RG01", "RG02", "RG03", "RI03", "RI04", "RJ03", "RJ05", "RJ06", "RJ07"], 0.2890909090909091], [["RB01", "RC01", "RC02", "RC03"], 0.22666666666666663], [["RB02", "RB03", "RC03", "RC04", "RC05"], 0.29999999999999993], [["RF03", "RF04", "RF05", "RF06", "RF07", "RF08", "RI03", "RI04", "RI05", "RJ06"], 0.2444444444444444]], "louvain_communities": [[["RF03", "RF04", "RF05", "RF06", "RF07", "RF08", "RI03", "RI04", "RI05", "RJ06"], 0.17777777777777776], [["RB01", "RC01", "RC02", "RC03"], 0.22666666666666663], [["RG01", "RG02", "RG03", "RJ03", "RJ04", "RJ05", "RJ06", "RJ07"], 0.29142857142857137], [["RG01", "RG02", "RG03", "RJ03", "RJ04", "RJ05", "RJ06", "RJ07"], 0.3985714285714286]], "kernighan_lin_bisection": [[["LA01", "LA03", "LA05", "LC01", "LE07", "LF03", "LG07", "RA01", "RA02", "RA06", "RA07", "RA08", "RB01", "RB02", "RB03", "RC01", "RC02", "RC03", "RC04", "RC05", "RC08", "RD06", "RD08", "RE01", "RE02", "RE04", "RE05", "RE06", "RE07", "RE08", "RF01", "RG06", "RG08", "RJ02"], 0], [["LA01", "LA03", "LA05", "LB01", "LC01", "LC03", "LC05", "LC07", "LD01", "LD03", "LD05", "LE07", "LF01", "LF03", "LG07", "RA06", "RB01", "RB04", "RB05", "RB06", "RB08", "RB09", "RB10", "RB11", "RB12", "RC01", "RC02", "RC03", "RC04", "RC05", "RC06", "RC07", "RC08", "RC11", "RC12", "RD01", "RD02", "RD03", "RD04", "RD07", "RD08", "RE02", "RE03", "RE04", "RE05", "RE06", "RE07", "RF02", "RG04", "RG05", "RG06", "RG07", "RH03", "RI02", "RJ01", "RJ02", "RJ08"], 0], [["LA01", "LA05", "LB01", "LB03", "LC07", "LD03", "LD05", "LE01", "LE07", "LF01", "LF03", "LG05", "RA01", "RA02", "RA03", "RA04", "RA05", "RA07", "RB01", "RB04", "RB05", "RB07", "RB08", "RB10", "RB11", "RB12", "RC01", "RC02", "RC06", "RC07", "RC08", "RC10", "RC11", "RC12", "RD06", "RE02", "RE04", "RE05", "RE06", "RE07", "RE08", "RG06", "RG07", "RG08", "RH01", "RH02", "RH03", "RH04", "RH05", "RH06", "RH07", "RH08", "RI01", "RI06", "RI07", "RI08", "RJ02"], 0], [["LA01", "LA07", "LB01", "LB03", "LB05", "LC03", "LC07", "LD03", "LE01", "LE03", "LE07", "LF03", "LF05", "LG01", "LG03", "LG05", "RA01", "RA02", "RA03", "RA04", "RA05", "RA07", "RB02", "RB03", "RB04", "RB07", "RB08", "RB09", "RC03", "RC06", "RC07", "RC08", "RC10", "RC11", "RC12", "RD01", "RD02", "RD03", "RD04", "RD07", "RD08", "RE03", "RF01", "RF02", "RG04", "RG05", "RG06", "RG07", "RG08", "RH02", "RH03", "RH04", "RH06", "RH08", "RJ01", "RJ02", "RJ08"], 0]]}