{"2_k_clique_communities": [[["LI1", "LI2", "LI3", "LI4", "LI5"], 0.29999999999999993], [["RF10", "RF11", "RF12", "RF9"], 0.56]], "3_k_clique_communities": [[["LI2", "LI3", "LI4", "LI5"], 0.56], [["RF10", "RF11", "RF12", "RF9"], 0.56]], "4_k_clique_communities": [[["LD2", "LD3", "LD4", "LD5", "LG4", "LG5", "LG6", "LG7"], 0.5771428571428571], [["LD1", "LD2", "LD3", "LG5", "LG6"], 0.6]], "girvan_newman": [[["LD1", "LD2", "LD3", "LD4", "LD5", "LG2", "LG3", "LG4", "LG5", "LG6", "LG7"], 0.3672727272727272], [["RF10", "RF11", "RF12", "RF9"], 0.56]], "2_edge_current_flow_betweenness_partition": [[["LI1", "LI2", "LI3", "LI4", "LI5"], 0.29999999999999993], [["RF10", "RF11", "RF12", "RF9"], 0.56]], "3_edge_current_flow_betweenness_partition": [[["LI1", "LI2", "LI3", "LI4", "LI5"], 0.29999999999999993], [["RF10", "RF11", "RF12", "RF9"], 0.56]], "4_edge_current_flow_betweenness_partition": [[["LI1", "LI2", "LI3", "LI4", "LI5"], 0.29999999999999993], [["RF10", "RF11", "RF12", "RF9"], 0.56]], "greedy_modularity_communities": [[["LD1", "LD2", "LD3", "LD4", "LD5", "LG2", "LG3", "LG4", "LG5", "LG6", "LG7"], 0.3672727272727272], [["RF10", "RF11", "RF12", "RF9"], 0.56]], "louvain_communities": [[["LD1", "LD2", "LD3", "LD4", "LD5", "LG2", "LG3", "LG4", "LG5", "LG6", "LG7"], 0.3672727272727272], [["RF10", "RF11", "RF12", "RF9"], 0.56]], "kernighan_lin_bisection": [[["LA1", "LA3", "LA8", "LB1", "LB2", "LB3", "LB5", "LB7", "LC10", "LC11", "LD1", "LD2", "LD3", "LD4", "LD5", "LD6", "LD7", "LD9", "LE7", "LE8", "LF4", "LG11", "LG12", "LG2", "LG3", "LG4", "LG5", "LG6", "LG7", "RA1", "RA7", "RA8", "RB2", "RB3", "RB4", "RB8", "RC1", "RC10", "RC11", "RC12", "RC2", "RC4", "RC5", "RC6", "RC7", "RC9", "RD1", "RD2", "RD3", "RD4", "RD5", "RD6", "RE1", "RE3", "RE5", "RF1", "RF5", "RG1", "RG10", "RG12", "RG2", "RG3", "RG4", "RG5", "RG6", "RG7", "RG8", "RG9", "RH10", "RH11", "RH12", "RH2", "RH3", "RH4", "RH5", "RH6", "RH7", "RH8", "RH9", "RJ1", "RJ10", "RJ11", "RJ2", "RJ3", "RJ5", "RJ8"], 0], [["LA1", "LA3", "LA7", "LB11", "LB12", "LB5", "LB6", "LB7", "LB8", "LC3", "LD1", "LD10", "LD11", "LD12", "LD2", "LD3", "LD4", "LD5", "LD6", "LD7", "LE2", "LE4", "LE6", "LF1", "LF4", "LG1", "LG2", "LG3", "LG4", "LG5", "LG6", "LG7", "LG8", "LI11", "LI12", "RA3", "RA4", "RA5", "RA6", "RA7", "RB1", "RB4", "RC1", "RC2", "RC3", "RE1", "RE3", "RE4", "RE5", "RE8", "RF4", "RF5", "RF6", "RF7", "RF8", "RG10", "RG12", "RG3", "RG4", "RG5", "RG6", "RG7", "RG8", "RG9", "RH1", "RH10", "RH11", "RH12", "RH2", "RH3", "RH4", "RH5", "RH6", "RH7", "RH8", "RH9", "RJ10", "RJ11", "RJ2", "RJ3", "RJ4", "RJ5", "RJ6", "RJ7", "RJ8", "RJ9"], 0]]}