{"2_k_clique_communities": [[["RA04", "RA05", "RA06", "RA07", "RA08", "RA09", "RA10", "RB01", "RB02", "RB03", "RB05", "RB06"], 0.33454545454545453], [["RB07", "RB08", "RB09", "RB10", "RB11", "RB12"], 0.30666666666666664]], "3_k_clique_communities": [[["RB09", "RB10", "RB11", "RB12"], 0.56], [["LD09", "LD10", "LD11", "LD12", "LE08", "LE09", "LE10", "LE11", "LE12", "LG12"], 0.6000000000000001]], "4_k_clique_communities": [[["LD05", "LD06", "LD07", "LD08"], 0.56], [["LD09", "LD10", "LD11", "LD12", "LE08", "LE09", "LE10", "LE11", "LE12", "LG12"], 0.6000000000000001]], "girvan_newman": [[["RA04", "RA05", "RA06", "RA07", "RA08", "RA09", "RA10", "RB01", "RB02", "RB03", "RB05", "RB06"], 0.33454545454545453], [["LD09", "LD10", "LD11", "LD12", "LE08", "LE09", "LE10", "LE11", "LE12", "LG12"], 0.6000000000000001]], "2_edge_current_flow_betweenness_partition": [[["RA04", "RA05", "RA06", "RA07", "RA08", "RA09", "RA10", "RB01", "RB02", "RB03", "RB05", "RB06"], 0.33454545454545453], [["RB07", "RB08", "RB09", "RB10", "RB11", "RB12"], 0.30666666666666664]], "3_edge_current_flow_betweenness_partition": [[["RA04", "RA05", "RA06", "RA07", "RA08", "RA09", "RA10", "RB01", "RB02", "RB03", "RB05", "RB06"], 0.33454545454545453], [["RB07", "RB08", "RB09", "RB10", "RB11", "RB12"], 0.30666666666666664]], "4_edge_current_flow_betweenness_partition": [[["RA04", "RA05", "RA06", "RA07", "RA08", "RA09", "RA10", "RB01", "RB02", "RB03", "RB05", "RB06"], 0.33454545454545453], [["RB07", "RB08", "RB09", "RB10", "RB11", "RB12"], 0.30666666666666664]], "greedy_modularity_communities": [[["LF05", "LF06", "LF07", "LF08", "LF09", "LF10"], 0.44000000000000006], [["LD09", "LD10", "LD11", "LD12", "LE08", "LE09", "LE10", "LE11", "LE12", "LG12"], 0.6000000000000001]], "louvain_communities": [[["LF05", "LF06", "LF07", "LF08", "LF09", "LF10"], 0.44000000000000006], [["LD09", "LD10", "LD11", "LD12", "LE08", "LE09", "LE10", "LE11", "LE12", "LG12"], 0.6000000000000001]], "kernighan_lin_bisection": [[["LC05", "LC06", "LD09", "LD10", "LD11", "LD12", "LE08", "LE09", "LE10", "LE11", "LE12", "LG12"], 0.30424242424242426], [["LA01", "LA02", "LA03", "LA04", "LA05", "LA06", "LA07", "LA08", "LA09", "LA10", "LB01", "LB02", "LB03", "LB04", "LB05", "LB06", "LB07", "LB08", "LB09", "LB10", "LB11", "LC02", "LC03", "LC04", "LC06", "LD03", "LD09", "LD10", "LD11", "LD12", "LE01", "LE08", "LE09", "LE10", "LE11", "LE12", "LF11", "LG01", "LG12", "RA04", "RA05", "RA06", "RA07", "RA08", "RA09", "RB01", "RB02", "RB03", "RB05", "RB06", "RB07", "RB08", "RB09", "RB10", "RB11", "RB12"], 0]]}