{"2_k_clique_communities": [[["RD4", "RD5", "RD6", "RD7", "RD8"], 0.6], [["RD4", "RD5", "RD6", "RD7", "RD8"], 0.6], [["RD4", "RD5", "RD6", "RD7", "RD8"], 0.6], [["RD4", "RD5", "RD6", "RD7", "RD8"], 0.6]], "3_k_clique_communities": [[["RD4", "RD5", "RD6", "RD7", "RD8"], 0.6], [["RD4", "RD5", "RD6", "RD7", "RD8"], 0.6], [["RD4", "RD5", "RD6", "RD7", "RD8"], 0.6], [["RD4", "RD5", "RD6", "RD7", "RD8"], 0.6]], "4_k_clique_communities": [[["RD4", "RD5", "RD6", "RD7", "RD8"], 0.6], [["RJ7", "RJ8", "RK7", "RK8", "RM7", "RM8"], 0.64], [["RD4", "RD5", "RD6", "RD7", "RD8"], 0.6], [["RD4", "RD5", "RD6", "RD7", "RD8"], 0.6]], "girvan_newman": [[["RD4", "RD5", "RD6", "RD7", "RD8"], 0.6], [["RD4", "RD5", "RD6", "RD7", "RD8"], 0.6], [["RD4", "RD5", "RD6", "RD7", "RD8"], 0.6], [["RD4", "RD5", "RD6", "RD7", "RD8"], 0.6]], "2_edge_current_flow_betweenness_partition": [[["RD4", "RD5", "RD6", "RD7", "RD8"], 0.6], [["RD4", "RD5", "RD6", "RD7", "RD8"], 0.6], [["RD4", "RD5", "RD6", "RD7", "RD8"], 0.6], [["RD4", "RD5", "RD6", "RD7", "RD8"], 0.6]], "3_edge_current_flow_betweenness_partition": [[["RD4", "RD5", "RD6", "RD7", "RD8"], 0.6], [["RD4", "RD5", "RD6", "RD7", "RD8"], 0.6], [["RD4", "RD5", "RD6", "RD7", "RD8"], 0.6], [["RD4", "RD5", "RD6", "RD7", "RD8"], 0.6]], "4_edge_current_flow_betweenness_partition": [[["RD4", "RD5", "RD6", "RD7", "RD8"], 0.6], [["RD4", "RD5", "RD6", "RD7", "RD8"], 0.6], [["RD4", "RD5", "RD6", "RD7", "RD8"], 0.6], [["RD4", "RD5", "RD6", "RD7", "RD8"], 0.6]], "greedy_modularity_communities": [[["RD4", "RD5", "RD6", "RD7", "RD8"], 0.6], [["RD4", "RD5", "RD6", "RD7", "RD8"], 0.6], [["RD4", "RD5", "RD6", "RD7", "RD8"], 0.6], [["RD4", "RD5", "RD6", "RD7", "RD8"], 0.6]], "louvain_communities": [[["RD4", "RD5", "RD6", "RD7", "RD8"], 0.6], [["RD4", "RD5", "RD6", "RD7", "RD8"], 0.6], [["RD4", "RD5", "RD6", "RD7", "RD8"], 0.6], [["RD4", "RD5", "RD6", "RD7", "RD8"], 0.6]], "kernighan_lin_bisection": [[["RA1", "RA10", "RA8", "RA9", "RB1", "RB5", "RB8", "RB9", "RC2", "RC8", "RD3", "RE2", "RE3", "RE4", "RE6", "RF2", "RF8", "RG1", "RG6", "RH1", "RH2", "RH3", "RH6", "RH7", "RI3", "RI4", "RI5", "RI6", "RI7", "RI8", "RJ2", "RK3", "RL2", "RM5", "RM6"], 0], [["RA1", "RA10", "RA2", "RA3", "RA7", "RA8", "RA9", "RB5", "RB7", "RC1", "RC2", "RC6", "RC7", "RC8", "RD1", "RD2", "RD3", "RE1", "RE10", "RE5", "RE7", "RE8", "RE9", "RF1", "RF2", "RF3", "RF4", "RF5", "RF6", "RF7", "RF8", "RG2", "RG3", "RG4", "RG7", "RH1", "RH2", "RH3", "RH4", "RI3", "RI4", "RI5", "RI6", "RI7", "RI8", "RJ1", "RJ2", "RJ6", "RK4", "RK5", "RL3", "RM1", "RM2", "RM3", "RM4", "RM6"], 0], [["RA1", "RA7", "RB1", "RB3", "RB4", "RB6", "RB7", "RC2", "RC5", "RD2", "RE7", "RE9", "RF1", "RF2", "RG1", "RG3", "RH1", "RH2", "RH3", "RH4", "RH5", "RH6", "RH7", "RI8", "RJ5", "RJ6", "RK1", "RK2", "RK4", "RK5", "RM1", "RM2", "RM3", "RM5"], 0], [["RA1", "RA3", "RA7", "RB10", "RB11", "RB8", "RB9", "RD1", "RE4", "RG5", "RG7", "RH4", "RH5", "RH6", "RI2", "RI3", "RI4", "RI5", "RI6", "RI7", "RJ2", "RJ4", "RK3", "RK4", "RK5", "RK6", "RK7", "RK8", "RL3", "RL4", "RM2", "RM4"], 0]]}