{"2_k_clique_communities": [[["RB05", "RB06", "RB07", "RG02"], 0.22666666666666663], [["LE03", "LE04", "LE05", "LE06"], 0.39333333333333337], [["RC06", "RC07", "RG05", "RG06"], 0.56], [["LE03", "LE04", "LE05", "LE06"], 0.39333333333333337]], "3_k_clique_communities": [[["LA02", "LA03", "LA04", "LD01"], 0.39333333333333337], [["LC06", "LC07", "LC08", "LC09", "LC10"], 0.4], [["RC06", "RC07", "RG05", "RG06"], 0.56], [["LE03", "LE04", "LE05", "LE06"], 0.39333333333333337]], "4_k_clique_communities": [[["LC07", "LC08", "LC09", "LC10"], 0.56], [["LC07", "LC08", "LC09", "LC10"], 0.56], [["RC06", "RC07", "RG05", "RG06"], 0.56], [["LC05", "LC06", "LC07", "LC08", "LC09", "LC10"], 0.44000000000000006]], "girvan_newman": [[["RB05", "RB06", "RB07", "RG02"], 0.22666666666666663], [["LA02", "LA03", "LA04", "LD01"], 0.39333333333333337], [["RC06", "RC07", "RG05", "RG06"], 0.56], [["LE03", "LE04", "LE05", "LE06"], 0.39333333333333337]], "2_edge_current_flow_betweenness_partition": [[["RB05", "RB06", "RB07", "RG02"], 0.22666666666666663], [["LE03", "LE04", "LE05", "LE06"], 0.39333333333333337], [["RC06", "RC07", "RG05", "RG06"], 0.56], [["LE03", "LE04", "LE05", "LE06"], 0.39333333333333337]], "3_edge_current_flow_betweenness_partition": [[["RB05", "RB06", "RB07", "RG02"], 0.22666666666666663], [["LE03", "LE04", "LE05", "LE06"], 0.39333333333333337], [["RC06", "RC07", "RG05", "RG06"], 0.56], [["LE03", "LE04", "LE05", "LE06"], 0.39333333333333337]], "4_edge_current_flow_betweenness_partition": [[["RB05", "RB06", "RB07", "RG02"], 0.22666666666666663], [["LE03", "LE04", "LE05", "LE06"], 0.39333333333333337], [["RC06", "RC07", "RG05", "RG06"], 0.56], [["LE03", "LE04", "LE05", "LE06"], 0.39333333333333337]], "greedy_modularity_communities": [[["RB05", "RB06", "RB07", "RG02"], 0.22666666666666663], [["LA02", "LA03", "LA04", "LD01"], 0.39333333333333337], [["RC06", "RC07", "RG05", "RG06"], 0.56], [["LE03", "LE04", "LE05", "LE06"], 0.39333333333333337]], "louvain_communities": [[["RB05", "RB06", "RB07", "RG02"], 0.22666666666666663], [["LA02", "LA03", "LA04", "LD01"], 0.39333333333333337], [["RC06", "RC07", "RG05", "RG06"], 0.56], [["LE03", "LE04", "LE05", "LE06"], 0.39333333333333337]], "kernighan_lin_bisection": [[["LA01", "LA08", "LC03", "LC04", "LC05", "LC06", "LC07", "LC08", "LC09", "LC10", "LD03", "LD04", "LD06", "LD07", "RB01", "RB05", "RB06", "RB07", "RC01", "RC02", "RE01", "RE05", "RF02", "RF03", "RF04", "RG02", "RG03", "RI02", "RI07", "RI08"], 0], [["LA01", "LA10", "LC01", "LC02", "LC04", "LC05", "LC06", "LC07", "LC08", "LC09", "LC10", "LE01", "LE02", "RA10", "RD01", "RD08", "RF02", "RF03", "RF04", "RF05", "RF06", "RF07", "RF08", "RG05", "RG06", "RH08", "RH09", "RH10", "RI01", "RI04", "RI06"], 0], [["LA01", "LA02", "LA03", "LA04", "LA06", "LA10", "LB01", "LB02", "LB03", "LB04", "LB05", "LB06", "LB07", "LB08", "LB09", "LB10", "LC01", "LD01", "LD06", "LE01", "LE07", "RA04", "RA05", "RA06", "RA07", "RA08", "RA09", "RA10", "RB03", "RB04", "RD01", "RD07", "RD08", "RE04", "RE05", "RG01", "RH01", "RI01", "RI03", "RI08"], 0], [["LA01", "LA03", "LA04", "LA05", "LA06", "LB01", "LB02", "LB03", "LB04", "LB05", "LB06", "LD01", "LD02", "LD03", "LD04", "LD05", "LE02", "LE08", "RA04", "RA05", "RA06", "RA07", "RA08", "RA09", "RA10", "RB01", "RB03", "RB04", "RB05", "RB06", "RB07", "RB09", "RB10", "RC02", "RC03", "RC04", "RC05", "RD06", "RD07", "RD08", "RE01", "RF01", "RF07", "RF08", "RG02", "RG04", "RH02", "RH03", "RH04", "RH05", "RH06", "RH07", "RI01", "RI03", "RI04", "RI05", "RI06", "RI07", "RI08"], 0]]}