{"2_k_clique_communities": [[["A'1", "H'1", "H'2", "H'3", "H'4", "H'5", "H'6", "T'1", "T'2", "T'3", "T'4", "T'5", "T'6", "T'7"], 0.6413186813186813]], "3_k_clique_communities": [[["A'1", "H'1", "H'2", "H'3", "H'4", "H'5", "H'6", "T'1", "T'2", "T'3", "T'4", "T'5", "T'6", "T'7"], 0.6413186813186813]], "4_k_clique_communities": [[["H'1", "H'2", "H'3", "H'4", "H'5", "H'6", "T'1", "T'2", "T'3", "T'4", "T'5", "T'6", "T'7"], 0.6892307692307693]], "girvan_newman": [[["A'1", "H'1", "H'2", "H'3", "H'4", "H'5", "H'6", "T'1", "T'2", "T'3", "T'4", "T'5", "T'6", "T'7"], 0.6413186813186813]], "2_edge_current_flow_betweenness_partition": [[["A'1", "H'1", "H'2", "H'3", "H'4", "H'5", "H'6", "T'1", "T'2", "T'3", "T'4", "T'5", "T'6", "T'7"], 0.6413186813186813]], "3_edge_current_flow_betweenness_partition": [[["A'1", "H'1", "H'2", "H'3", "H'4", "H'5", "H'6", "T'1", "T'2", "T'3", "T'4", "T'5", "T'6", "T'7"], 0.6413186813186813]], "4_edge_current_flow_betweenness_partition": [[["A'1", "H'1", "H'2", "H'3", "H'4", "H'5", "H'6", "T'1", "T'2", "T'3", "T'4", "T'5", "T'6", "T'7"], 0.6413186813186813]], "greedy_modularity_communities": [[["A'1", "H'1", "H'2", "H'3", "H'4", "H'5", "H'6", "T'1", "T'2", "T'3", "T'4", "T'5", "T'6", "T'7"], 0.6413186813186813]], "louvain_communities": [[["A'1", "H'1", "H'2", "H'3", "H'4", "H'5", "H'6", "T'1", "T'2", "T'3", "T'4", "T'5", "T'6", "T'7"], 0.6413186813186813]], "kernighan_lin_bisection": [[["TP'1", "TP'2", "TP'3", "TP'4", "TP'5", "TP'6", "TP'7", "A'3", "A'4", "A'5", "A'6", "A'7", "A'8", "A'9", "B'4", "B'5", "B'6", "B'7", "B'8", "B'9", "C'2", "C'3", "C'4", "C'5", "C'6", "C'7", "C'8", "C'9", "GPH'1", "GPH'2", "GPH'3", "GPH'4", "GPH'5", "GPH'6", "GPH'7", "GPH'8", "GPH'9", "OT'1", "OT'2", "OT'3", "OT'4", "OT'5", "FCA'4", "FCA'5", "FCA'6", "FCA'7", "FCA'8", "FCA'9", "GL'1", "GL'2", "GL'3", "GL'4", "GL'5", "GL'6", "GL'7", "GL'8", "GL'9", "Cu'1", "Cu'2", "Cu'3", "Cu'4", "Cu'5", "Cu'6", "Cu'7", "Cu'8", "Cu'9", "PFG'6", "PFG'7", "PFG'8", "PFG'9", "PP'7", "PP'9", "PA'6", "PA'8", "PA'9", "GC'5", "GC'6", "GC'7", "GC'8", "GC'9", "LP'1", "LP'2", "LP'3", "LP'4", "LP'5", "LP'6", "LP'7", "LP'8", "LP'9", "FD'8", "FD'9", "CR'1", "CR'2", "CR'3", "CR'4", "CR'5", "CR'6", "CR'7", "CR'8", "CR'9", "R'1", "R'2", "R'3", "R'4", "R'5", "R'6", "R'8", "R'9", "OR'1", "OR'2", "OR'3", "OR'4", "OR'5", "OR'6", "OR'7", "OR'8", "OR'9", "FT'1", "FT'2", "FT'3", "FT'4", "FT'5", "FT'6", "FT'7", "FT'8", "FT'9", "SC'8", "SC'9", "OF'4", "OF'5", "OF'6", "OF'7", "OF'8", "OF'9", "OC'1", "OC'2", "OC'3", "OC'5", "OC'6", "OC'7", "OC'8", "OP'6", "OP'7", "OP'8", "OP'9", "H'9", "T'9"], 0]]}