{"2_k_clique_communities": [[["LB02", "LB03", "LB04", "LB05", "LB06"], 0.6], [["LB02", "LB03", "LB04", "LB05", "LB06"], 0.6], [["LB02", "LB03", "LB04", "LB05", "LB06"], 0.6], [["LB02", "LB03", "LB04", "LB05", "LB06"], 0.6], [["LB02", "LB03", "LB04", "LB05", "LB06"], 0.6], [["LB02", "LB03", "LB04", "LB05", "LB06"], 0.6], [["LB02", "LB03", "LB04", "LB05", "LB06"], 0.6], [["LB02", "LB03", "LB04", "LB05", "LB06"], 0.6], [["LB02", "LB03", "LB04", "LB05", "LB06"], 0.6], [["LB02", "LB03", "LB04", "LB05", "LB06"], 0.6]], "3_k_clique_communities": [[["LB02", "LB03", "LB04", "LB05", "LB06"], 0.6], [["LB02", "LB03", "LB04", "LB05", "LB06"], 0.6], [["LB02", "LB03", "LB04", "LB05", "LB06"], 0.6], [["LB02", "LB03", "LB04", "LB05", "LB06"], 0.6], [["LB02", "LB03", "LB04", "LB05", "LB06"], 0.6], [["LB02", "LB03", "LB04", "LB05", "LB06"], 0.6], [["LB02", "LB03", "LB04", "LB05", "LB06"], 0.6], [["LB02", "LB03", "LB04", "LB05", "LB06"], 0.6], [["LB02", "LB03", "LB04", "LB05", "LB06"], 0.6], [["LB02", "LB03", "LB04", "LB05", "LB06"], 0.6]], "4_k_clique_communities": [[["LB02", "LB03", "LB04", "LB05", "LB06"], 0.6], [["LB02", "LB03", "LB04", "LB05", "LB06"], 0.6], [["LB02", "LB03", "LB04", "LB05", "LB06"], 0.6], [["LB02", "LB03", "LB04", "LB05", "LB06"], 0.6], [["LB02", "LB03", "LB04", "LB05", "LB06"], 0.6], [["LB02", "LB03", "LB04", "LB05", "LB06"], 0.6], [["LB02", "LB03", "LB04", "LB05", "LB06"], 0.6], [["LB02", "LB03", "LB04", "LB05", "LB06"], 0.6], [["LB02", "LB03", "LB04", "LB05", "LB06"], 0.6], [["LB02", "LB03", "LB04", "LB05", "LB06"], 0.6]], "girvan_newman": [[["LB02", "LB03", "LB04", "LB05", "LB06"], 0.6], [["LB02", "LB03", "LB04", "LB05", "LB06"], 0.6], [["LB02", "LB03", "LB04", "LB05", "LB06"], 0.6], [["LB02", "LB03", "LB04", "LB05", "LB06"], 0.6], [["LB02", "LB03", "LB04", "LB05", "LB06"], 0.6], [["LB02", "LB03", "LB04", "LB05", "LB06"], 0.6], [["LB02", "LB03", "LB04", "LB05", "LB06"], 0.6], [["LB02", "LB03", "LB04", "LB05", "LB06"], 0.6], [["LB02", "LB03", "LB04", "LB05", "LB06"], 0.6], [["LB02", "LB03", "LB04", "LB05", "LB06"], 0.6]], "2_edge_current_flow_betweenness_partition": [[["LB02", "LB03", "LB04", "LB05", "LB06"], 0.6], [["LB02", "LB03", "LB04", "LB05", "LB06"], 0.6], [["LB02", "LB03", "LB04", "LB05", "LB06"], 0.6], [["LB02", "LB03", "LB04", "LB05", "LB06"], 0.6], [["LB02", "LB03", "LB04", "LB05", "LB06"], 0.6], [["LB02", "LB03", "LB04", "LB05", "LB06"], 0.6], [["LB02", "LB03", "LB04", "LB05", "LB06"], 0.6], [["LB02", "LB03", "LB04", "LB05", "LB06"], 0.6], [["LB02", "LB03", "LB04", "LB05", "LB06"], 0.6], [["LB02", "LB03", "LB04", "LB05", "LB06"], 0.6]], "3_edge_current_flow_betweenness_partition": [[["LB02", "LB03", "LB04", "LB05", "LB06"], 0.6], [["LB02", "LB03", "LB04", "LB05", "LB06"], 0.6], [["LB02", "LB03", "LB04", "LB05", "LB06"], 0.6], [["LB02", "LB03", "LB04", "LB05", "LB06"], 0.6], [["LB02", "LB03", "LB04", "LB05", "LB06"], 0.6], [["LB02", "LB03", "LB04", "LB05", "LB06"], 0.6], [["LB02", "LB03", "LB04", "LB05", "LB06"], 0.6], [["LB02", "LB03", "LB04", "LB05", "LB06"], 0.6], [["LB02", "LB03", "LB04", "LB05", "LB06"], 0.6], [["LB02", "LB03", "LB04", "LB05", "LB06"], 0.6]], "4_edge_current_flow_betweenness_partition": [[["LB02", "LB03", "LB04", "LB05", "LB06"], 0.6], [["LB02", "LB03", "LB04", "LB05", "LB06"], 0.6], [["LB02", "LB03", "LB04", "LB05", "LB06"], 0.6], [["LB02", "LB03", "LB04", "LB05", "LB06"], 0.6], [["LB02", "LB03", "LB04", "LB05", "LB06"], 0.6], [["LB02", "LB03", "LB04", "LB05", "LB06"], 0.6], [["LB02", "LB03", "LB04", "LB05", "LB06"], 0.6], [["LB02", "LB03", "LB04", "LB05", "LB06"], 0.6], [["LB02", "LB03", "LB04", "LB05", "LB06"], 0.6], [["LB02", "LB03", "LB04", "LB05", "LB06"], 0.6]], "greedy_modularity_communities": [[["LB02", "LB03", "LB04", "LB05", "LB06"], 0.6], [["LB02", "LB03", "LB04", "LB05", "LB06", "LE06", "RI08"], 0.15619047619047616], [["LB02", "LB03", "LB04", "LB05", "LB06", "LE06", "LH02", "RI03", "RI06", "RI08"], 0.0222222222222222], [["LH04", "LH05", "LH06", "LI07"], 0.22666666666666663], [["LB02", "LB03", "LB04", "LB05", "LB06", "LE04", "LG08", "LH06", "LI02", "LI06", "RI03", "RI06"], 0.03151515151515154], [["LB02", "LB03", "LB04", "LB05", "LB06", "LD04", "LE04", "LE05", "LG08", "LH06", "RI06"], 0.02181818181818182], [["LB02", "LB03", "LB04", "LB05", "LB06", "LE05", "LH04", "LH06", "LI02", "LI03", "LI06", "RI03", "RI06", "RI08"], 0.08087912087912089], [["LB02", "LB03", "LB04", "LB05", "LB06", "LC01", "LE04", "LE05", "LH06", "LI02", "LI06", "RI03", "RI06", "RI08"], 0.06989010989010988], [["LB02", "LB03", "LB04", "LB05", "LB06", "LC01", "LD04", "LE04", "LE05", "LG03", "LG08", "LH06", "LI02", "RI05", "RI06", "RI08"], 0.04333333333333333], [["LB02", "LB03", "LB04", "LB05", "LB06", "LC01", "LD04", "LE04", "LG03", "LG08", "LH06", "LI02", "RI06", "RI08"], 0.06989010989010988]], "louvain_communities": [[["LB02", "LB03", "LB04", "LB05", "LB06"], 0.6], [["LB02", "LB03", "LB04", "LB05", "LB06"], 0.6], [["LB02", "LB03", "LB04", "LB05", "LB06"], 0.6], [["LB02", "LB03", "LB04", "LB05", "LB06"], 0.6], [["LB02", "LB03", "LB04", "LB05", "LB06"], 0.6], [["LB02", "LB03", "LB04", "LB05", "LB06"], 0.6], [["LB02", "LB03", "LB04", "LB05", "LB06"], 0.6], [["LB02", "LB03", "LB04", "LB05", "LB06"], 0.6], [["LB02", "LB03", "LB04", "LB05", "LB06"], 0.6], [["LB02", "LB03", "LB04", "LB05", "LB06"], 0.6]], "kernighan_lin_bisection": [[["LA03", "LB02", "LB03", "LB04", "LB05", "LB06", "LD02", "LG01", "LG06", "LH06", "LH07", "RI01", "RI08", "RI09"], 0.08087912087912089], [["LA01", "LA05", "LA06", "LB01", "LC01", "LC02", "LC03", "LC04", "LD01", "LD02", "LD03", "LD04", "LE02", "LE03", "LF02", "LF05", "LF06", "LG03", "LG05", "LH01", "LH02", "LH05", "LI01", "LI02", "LI03", "LI04", "LI05", "LI07", "LI09", "RI02", "RI03", "RI04", "RI05", "RI06", "RI07", "RI08", "RI11"], 0], [["LA01", "LA05", "LB01", "LB02", "LB03", "LB04", "LB05", "LB06", "LE01", "LG08", "LG09", "LG10", "LH07", "LI02", "LI03", "LI04", "LI08", "RI09"], 0], [["LA01", "LC02", "LD03", "LD04", "LE02", "LF05", "LF07", "LF08", "LG02", "LG05", "LG06", "LG07", "LH08", "LI01", "RI01", "RI09"], 0], [["LA01", "LA03", "LA06", "LC01", "LD01", "LD03", "LD04", "LE02", "LE03", "LE05", "LE06", "LG04", "LG05", "LG08", "LH01", "LH02", "LH08", "LI09", "RI01", "RI03", "RI04", "RI05", "RI06", "RI08", "RI09"], 0], [["LB02", "LB03", "LB04", "LB05", "LB06", "LD01", "LD04", "LE04", "LF02", "LF06", "LG08", "LH04", "LH05", "LI06", "LI07", "RI12"], 0.060000000000000005], [["LA01", "LB02", "LB03", "LB04", "LB05", "LB06", "LD01", "LD02", "LE01", "LF02", "LF03", "LG01", "LG02", "LG03", "LI02", "LI03", "LI08", "RI01", "RI03", "RI12"], 0], [["LA02", "LC02", "LC03", "LC04", "LD02", "LE04", "LG06", "LG08", "LG09", "LG10", "LH01", "LH02", "LI08", "RI03", "RI08", "RI10"], 0.018333333333333333], [["LA01", "LA02", "LA06", "LB02", "LB03", "LB04", "LB05", "LB06", "LC02", "LC03", "LC04", "LD03", "LD04", "LE04", "LF01", "LF02", "LF06", "LF07", "LF08", "LG04", "LG05", "LG07", "LG08", "LH04", "LH05", "LH06", "LH07", "LH08", "LI01", "LI02", "LI05", "LI06", "LI07", "RI07", "RI08", "RI09", "RI11"], 0], [["LC02", "LC03", "LC04", "LD03", "LF02", "LF04", "LF05", "LF07", "LF08", "LG04", "LI08", "LI09", "RI06", "RI09", "RI10"], 0.02857142857142857]]}