{"2_k_clique_communities": [[["LB02", "LB03", "LB04", "LB05", "LB06"], 0.6], [["LB02", "LB03", "LB04", "LB05"], 0.56]], "3_k_clique_communities": [[["LB02", "LB03", "LB04", "LB05", "LB06"], 0.6], [["LB02", "LB03", "LB04", "LB05"], 0.56]], "4_k_clique_communities": [[["LB02", "LB03", "LB04", "LB05", "LB06"], 0.6], [["LB02", "LB03", "LB04", "LB05"], 0.56]], "girvan_newman": [[["LB02", "LB03", "LB04", "LB05", "LB06"], 0.6], [["LB02", "LB03", "LB04", "LB05"], 0.56]], "2_edge_current_flow_betweenness_partition": [[["LB02", "LB03", "LB04", "LB05", "LB06"], 0.6], [["LB02", "LB03", "LB04", "LB05"], 0.56]], "3_edge_current_flow_betweenness_partition": [[["LB02", "LB03", "LB04", "LB05", "LB06"], 0.6], [["LB02", "LB03", "LB04", "LB05"], 0.56]], "4_edge_current_flow_betweenness_partition": [[["LB02", "LB03", "LB04", "LB05", "LB06"], 0.6], [["LB02", "LB03", "LB04", "LB05"], 0.56]], "greedy_modularity_communities": [[["LB02", "LB03", "LB04", "LB05", "LB06"], 0.6], [["LH04", "LH05", "LI07", "LI08"], 0.22666666666666663]], "louvain_communities": [[["LB02", "LB03", "LB04", "LB05", "LB06"], 0.6], [["LB02", "LB03", "LB04", "LB05"], 0.56]], "kernighan_lin_bisection": [[["LA01", "LA02", "LA05", "LB01", "LE02", "LE03", "LE04", "LG03", "LG08", "LG09", "LG10", "LH02", "LH06", "LI04", "RI02"], 0.0380952380952381], [["LA01", "LA02", "LA05", "LA06", "LB01", "LC02", "LC03", "LC04", "LF02", "LF03", "LF07", "LF08", "LG03", "LG06", "LG07", "LI02", "LI09", "RI07", "RI09", "RI12"], 0]]}