{"2_k_clique_communities": [[["RA01", "RA02", "RA03", "RA04", "RB01", "RB02", "RB03", "RB04", "RB05", "RC01", "RD01", "RD06", "RD07", "RD09", "RE01", "RE05", "RE06", "RE07", "RG02"], 0], [["RA01", "RA02", "RA03", "RA04", "RB01", "RB02", "RB03", "RD01", "RD06", "RD07", "RD09", "RE01", "RE03", "RE05", "RE06", "RG02", "RG03", "RG04", "RG08"], 0], [["RA01", "RA02", "RA03", "RA04", "RA05", "RB01", "RB02", "RB03", "RB04", "RB05", "RC01", "RD01", "RD06", "RD07", "RD09", "RE01", "RE04", "RE05", "RE06", "RG01", "RG02", "RG08", "RG09", "RG10", "RG11"], 0], [["RA01", "RA02", "RA03", "RA04", "RA05", "RB01", "RB02", "RB03", "RB04", "RB05", "RB12", "RC01", "RC02", "RG08", "RG09", "RG10", "RG11", "RH01", "RH11"], 0]], "3_k_clique_communities": [[["RA06", "RD12", "RF01", "RF02", "RF03", "RF04", "RH10", "RH12"], 0.32714285714285707], [["RA01", "RA02", "RA03", "RA04", "RA05", "RA06", "RA07", "RA08", "RB01", "RB02", "RB03", "RB04", "RB05", "RB06", "RB07", "RB08", "RB09", "RB10", "RB11", "RB12", "RC01", "RC02", "RC03", "RC04", "RC05", "RC06", "RC07", "RC08", "RC09", "RC11", "RC12", "RD01", "RD02", "RD03", "RD04", "RD05", "RD06", "RD07", "RD08", "RD09", "RD11", "RD12", "RE01", "RE02", "RE03", "RE04", "RE05", "RE06", "RE07", "RE08", "RE09", "RE10", "RE11", "RE12", "RF01", "RF02", "RF03", "RF04", "RF05", "RF07", "RF08", "RF09", "RF10", "RF11", "RF12", "RG01", "RG02", "RG03", "RG04", "RG05", "RG06", "RG08", "RG09", "RG10", "RG11", "RH01", "RH02", "RH03", "RH04", "RH05", "RH06", "RH07", "RH08", "RH09", "RH10", "RH11", "RH12"], 0], [["RA01", "RA02", "RA03", "RA04", "RA05", "RA06", "RA07", "RA08", "RB01", "RB02", "RB03", "RB04", "RB05", "RB06", "RB07", "RB08", "RB09", "RB10", "RB11", "RB12", "RC01", "RC02", "RC03", "RC04", "RC05", "RC06", "RC07", "RC08", "RC09", "RC11", "RC12", "RD01", "RD02", "RD03", "RD04", "RD05", "RD06", "RD07", "RD08", "RD09", "RD11", "RD12", "RE01", "RE02", "RE03", "RE04", "RE05", "RE06", "RE07", "RE08", "RE09", "RE10", "RE11", "RE12", "RF01", "RF02", "RF03", "RF04", "RF05", "RF07", "RF08", "RF09", "RF10", "RF11", "RF12", "RG01", "RG02", "RG03", "RG04", "RG05", "RG06", "RG08", "RG09", "RG10", "RG11", "RH01", "RH02", "RH03", "RH04", "RH05", "RH06", "RH07", "RH08", "RH09", "RH10", "RH11", "RH12"], 0], [["RA06", "RA07", "RA08", "RC06", "RC08", "RC09", "RD08", "RD11", "RD12", "RE06", "RE07", "RE08", "RE12", "RF01", "RF02", "RF03", "RF04", "RF05", "RG06", "RH06", "RH07", "RH08", "RH09", "RH10"], 0.08202898550724641]], "4_k_clique_communities": [[["RA01", "RA02", "RA03", "RA04", "RA05", "RA06", "RA07", "RA08", "RB01", "RB02", "RB03", "RB04", "RB05", "RB06", "RB07", "RB08", "RB09", "RB10", "RB11", "RB12", "RC01", "RC02", "RC03", "RC04", "RC05", "RC06", "RC07", "RC08", "RC09", "RC11", "RC12", "RD01", "RD02", "RD03", "RD04", "RD05", "RD06", "RD07", "RD08", "RD09", "RD11", "RD12", "RE01", "RE02", "RE03", "RE04", "RE05", "RE06", "RE07", "RE08", "RE09", "RE10", "RE11", "RE12", "RF01", "RF02", "RF03", "RF04", "RF05", "RF07", "RF08", "RF09", "RF10", "RF11", "RF12", "RG01", "RG02", "RG03", "RG04", "RG05", "RG06", "RG08", "RG09", "RG10", "RG11", "RH01", "RH02", "RH03", "RH04", "RH05", "RH06", "RH07", "RH08", "RH09", "RH10", "RH11", "RH12"], 0], [["RA01", "RA02", "RA03", "RA04", "RA05", "RA06", "RA07", "RA08", "RB01", "RB02", "RB03", "RB04", "RB05", "RB06", "RB07", "RB08", "RB09", "RB10", "RB11", "RB12", "RC01", "RC02", "RC03", "RC04", "RC05", "RC06", "RC07", "RC08", "RC09", "RC11", "RC12", "RD01", "RD02", "RD03", "RD04", "RD05", "RD06", "RD07", "RD08", "RD09", "RD11", "RD12", "RE01", "RE02", "RE03", "RE04", "RE05", "RE06", "RE07", "RE08", "RE09", "RE10", "RE11", "RE12", "RF01", "RF02", "RF03", "RF04", "RF05", "RF07", "RF08", "RF09", "RF10", "RF11", "RF12", "RG01", "RG02", "RG03", "RG04", "RG05", "RG06", "RG08", "RG09", "RG10", "RG11", "RH01", "RH02", "RH03", "RH04", "RH05", "RH06", "RH07", "RH08", "RH09", "RH10", "RH11", "RH12"], 0], [["RA01", "RA02", "RA03", "RA04", "RA05", "RA06", "RA07", "RA08", "RB01", "RB02", "RB03", "RB04", "RB05", "RB06", "RB07", "RB08", "RB09", "RB10", "RB11", "RB12", "RC01", "RC02", "RC03", "RC04", "RC05", "RC06", "RC07", "RC08", "RC09", "RC11", "RC12", "RD01", "RD02", "RD03", "RD04", "RD05", "RD06", "RD07", "RD08", "RD09", "RD11", "RD12", "RE01", "RE02", "RE03", "RE04", "RE05", "RE06", "RE07", "RE08", "RE09", "RE10", "RE11", "RE12", "RF01", "RF02", "RF03", "RF04", "RF05", "RF07", "RF08", "RF09", "RF10", "RF11", "RF12", "RG01", "RG02", "RG03", "RG04", "RG05", "RG06", "RG08", "RG09", "RG10", "RG11", "RH01", "RH02", "RH03", "RH04", "RH05", "RH06", "RH07", "RH08", "RH09", "RH10", "RH11", "RH12"], 0], [["RA01", "RA02", "RA03", "RA04", "RA05", "RA06", "RA07", "RA08", "RB01", "RB02", "RB03", "RB04", "RB05", "RB06", "RB07", "RB08", "RB09", "RB10", "RB11", "RB12", "RC01", "RC02", "RC03", "RC04", "RC05", "RC06", "RC07", "RC08", "RC09", "RC11", "RC12", "RD01", "RD02", "RD03", "RD04", "RD05", "RD06", "RD07", "RD08", "RD09", "RD11", "RD12", "RE01", "RE02", "RE03", "RE04", "RE05", "RE06", "RE07", "RE08", "RE09", "RE10", "RE11", "RE12", "RF01", "RF02", "RF03", "RF04", "RF05", "RF07", "RF08", "RF09", "RF10", "RF11", "RF12", "RG01", "RG02", "RG03", "RG04", "RG05", "RG06", "RG08", "RG09", "RG10", "RG11", "RH01", "RH02", "RH03", "RH04", "RH05", "RH06", "RH07", "RH08", "RH09", "RH10", "RH11", "RH12"], 0]], "girvan_newman": [[["RA01"], 0], [["RA01", "RE03", "RG03", "RG04", "RG08"], 0], [["RA01", "RA05", "RB04", "RB05", "RC01", "RE02", "RE04", "RG01", "RG08", "RG09", "RG10", "RG11"], 0], [["RA01", "RA05", "RB04", "RB05", "RB12", "RC01", "RC02", "RF12", "RG08", "RG09", "RG10", "RG11", "RH01", "RH11"], 0]], "2_edge_current_flow_betweenness_partition": [[["RA01"], 0], [["RA01", "RE03", "RG03", "RG04", "RG08"], 0], [["RA01"], 0], [["RA01"], 0]], "3_edge_current_flow_betweenness_partition": [[["RA01"], 0], [["RA01", "RE03", "RG03", "RG04", "RG08"], 0], [["RA01"], 0], [["RA01"], 0]], "4_edge_current_flow_betweenness_partition": [[["RA01"], 0], [["RA01", "RE03", "RG03", "RG04", "RG08"], 0], [["RA01"], 0], [["RA01"], 0]], "greedy_modularity_communities": [[["RA01"], 0], [["RC09", "RD02", "RD03", "RD04", "RD05", "RD08", "RD11", "RE02", "RE04", "RG01", "RG05", "RG06", "RG09", "RH06", "RH09", "RH10", "RH12"], 0.16264705882352942], [["RC08", "RC09", "RD02", "RD03", "RD04", "RD05", "RD08", "RD11", "RE02", "RE03", "RG03", "RG04", "RG05", "RG06", "RH06", "RH07", "RH09", "RH10"], 0.1675816993464052], [["RA01"], 0]], "louvain_communities": [[["RB07", "RB08", "RB10", "RC05", "RC08", "RD08", "RD11", "RE12", "RF07", "RF08", "RH02", "RH03", "RH04", "RH05", "RH07", "RH08"], 0.29333333333333333], [["RB07", "RB08", "RB09", "RB10", "RB11", "RC04", "RC05", "RC08", "RC11", "RD08", "RD12", "RE12", "RF05", "RF07", "RF08", "RF09", "RH01", "RH02", "RH03", "RH05", "RH07", "RH08"], 0.1225974025974026], [["RA06", "RA07", "RA08", "RB06", "RB12", "RC02", "RC03", "RC05", "RE07", "RE10", "RF01", "RF02", "RF03"], 0.3046153846153846], [["RA07", "RB06", "RB11", "RC03", "RC04", "RE06", "RE07", "RE08", "RE09", "RE10", "RF01", "RF02", "RF03", "RF05", "RH02", "RH03"], 0.32666666666666666]], "kernighan_lin_bisection": [[["RA01", "RA02", "RA03", "RA04", "RA05", "RA06", "RA07", "RB01", "RB02", "RB03", "RB04", "RB05", "RC01", "RD01", "RD02", "RD03", "RD04", "RD05", "RD06", "RD07", "RD09", "RE01", "RE02", "RE03", "RE04", "RE05", "RE06", "RE07", "RE09", "RF10", "RF11", "RF12", "RG01", "RG02", "RG03", "RG04", "RG05", "RG06", "RG08", "RG09", "RG10", "RG11", "RH10", "RH12"], 0], [["RA01", "RA02", "RA03", "RA04", "RA05", "RA07", "RB01", "RB02", "RB03", "RB04", "RD01", "RD02", "RD03", "RD04", "RD05", "RD06", "RD07", "RD09", "RD11", "RE01", "RE02", "RE03", "RE04", "RE05", "RE06", "RE07", "RF10", "RF11", "RF12", "RG01", "RG02", "RG03", "RG04", "RG05", "RG06", "RG08", "RG09", "RG10", "RG11", "RH10", "RH11", "RH12"], 0], [["RA01", "RA02", "RA03", "RA04", "RA05", "RA06", "RA07", "RB01", "RB02", "RB03", "RB04", "RB05", "RC01", "RC02", "RD01", "RD02", "RD03", "RD04", "RD05", "RD06", "RD07", "RD09", "RE01", "RE02", "RE03", "RE04", "RE05", "RE06", "RE07", "RF10", "RF12", "RG01", "RG02", "RG03", "RG04", "RG05", "RG08", "RG09", "RG10", "RG11", "RH09", "RH10"], 0], [["RA01", "RA02", "RA03", "RA04", "RA05", "RB01", "RB02", "RB03", "RB04", "RB05", "RB12", "RC01", "RC02", "RC08", "RD01", "RD02", "RD03", "RD04", "RD05", "RD06", "RD07", "RD09", "RE01", "RE02", "RE03", "RE04", "RE05", "RG01", "RG02", "RG03", "RG04", "RG05", "RG06", "RG08", "RG09", "RG10", "RG11", "RH01", "RH06", "RH07", "RH08", "RH09", "RH11", "RH12"], 0]]}