{"2_k_clique_communities": [[["HIPP1", "HIPP2", "HIPP3", "HIPP4", "MTG1", "MTG2"], 0.30666666666666664]], "3_k_clique_communities": [[["OF1", "OF2", "OF3", "OF4"], 0.56]], "4_k_clique_communities": [[["OF1", "OF2", "OF3", "OF4"], 0.56]], "girvan_newman": [[["HIPP1", "HIPP2", "HIPP3", "HIPP4", "MTG1", "MTG2"], 0.30666666666666664]], "2_edge_current_flow_betweenness_partition": [[["HIPP1", "HIPP2", "HIPP3", "HIPP4", "MTG1", "MTG2"], 0.30666666666666664]], "3_edge_current_flow_betweenness_partition": [[["HIPP1", "HIPP2", "HIPP3", "HIPP4", "MTG1", "MTG2"], 0.30666666666666664]], "4_edge_current_flow_betweenness_partition": [[["HIPP1", "HIPP2", "HIPP3", "HIPP4", "MTG1", "MTG2"], 0.30666666666666664]], "greedy_modularity_communities": [[["OF1", "OF2", "OF3", "OF4"], 0.56]], "louvain_communities": [[["CING-P1", "CING-P2", "CING-P3", "CING-P4"], 0.56]], "kernighan_lin_bisection": [[["ACCC4", "HIPP1", "HIPP2", "HIPP3", "HIPP4", "INS-P2", "MTG1", "MTG2", "MTG3", "MTG4", "OF1", "OF2", "OF3", "OF4", "OFAL3", "PIFG-4"], 0.10166666666666666]]}